djangocms_who_is_who/__init__.py
djangocms_who_is_who/admin.py
djangocms_who_is_who/apps.py
djangocms_who_is_who/cms_plugins.py
djangocms_who_is_who/forms.py
djangocms_who_is_who/models.py
djangocms_who_is_who/views.py
djangocms_who_is_who/migrations/0001_initial.py
djangocms_who_is_who/migrations/__init__.py
djangocms_who_is_who/static/djangocms_who_is_who/js/toggle_password.js
djangocms_who_is_who/templates/djangocms_who_is_who/djangocms_who_is_who.html.jinja
scout_ch_djangocms_who_is_who-0.1.0.dist-info/licenses/LICENSE
scout_ch_djangocms_who_is_who-0.1.0.dist-info/METADATA
scout_ch_djangocms_who_is_who-0.1.0.dist-info/WHEEL
scout_ch_djangocms_who_is_who-0.1.0.dist-info/top_level.txt
scout_ch_djangocms_who_is_who-0.1.0.dist-info/RECORD
