Metadata-Version: 2.4
Name: scout-ch-djangocms-who-is-who
Version: 0.1.0
Summary: This plugin serves to include the data generated by the Who-Is-Who application in a django-cms application
Requires-Python: >=3.13
License-File: LICENSE
Requires-Dist: django-cms>=5.0.4
Requires-Dist: pip>=25.3
Requires-Dist: requests>=2.32.5
Dynamic: license-file
